redis_tryton.py
redis_tryton-0.4.dist-info/DESCRIPTION.rst
redis_tryton-0.4.dist-info/METADATA
redis_tryton-0.4.dist-info/RECORD
redis_tryton-0.4.dist-info/WHEEL
redis_tryton-0.4.dist-info/metadata.json
redis_tryton-0.4.dist-info/top_level.txt
