Metadata-Version: 2.0
Name: redis-tryton
Version: 0.4
Summary: Redis Cache for the Tryton Framework
Home-page: https://bitbucket.org/pokoli/redis-tryton/
Author: Sergi Almacellas Abellana
Author-email: sergi@koolpi.com
License: GPL-3
Keywords: redis tryton cache
Platform: any
Classifier: Framework :: Tryton
Classifier: Intended Audience :: Developers
Classifier: License :: OSI Approved :: GNU General Public License (GPL)
Classifier: Operating System :: OS Independent
Classifier: Programming Language :: Python :: 2.7
Classifier: Programming Language :: Python :: 3.4
Classifier: Programming Language :: Python :: 3.5
Classifier: Programming Language :: Python :: 3.6
Classifier: Topic :: Software Development :: Libraries :: Python Modules
Requires-Dist: redis
Requires-Dist: msgpack-python
Requires-Dist: trytond (>=4.2)
